{
    "nodes": [
        {
            "id": "nickel",
            "group": "MINERAL",
            "degree": "5"
        },
        {
            "id": "tungsten",
            "group": "MINERAL",
            "degree": "1"
        },
        {
            "id": "arsenic",
            "group": "MINERAL",
            "degree": "6"
        },
        {
            "id": "lode gold deposit",
            "group": "ORE_DEPOSIT",
            "degree": "12"
        },
        {
            "id": "anthophyllite",
            "group": "MINERAL",
            "degree": "7"
        },
        {
            "id": "carbonate",
            "group": "MINERAL",
            "degree": "14"
        },
        {
            "id": "k feldspar",
            "group": "MINERAL",
            "degree": "1"
        },
        {
            "id": "lode",
            "group": "ORE_DEPOSIT",
            "degree": "37"
        },
        {
            "id": "rare earth element",
            "group": "MINERAL",
            "degree": "1"
        },
        {
            "id": "sulphide",
            "group": "MINERAL",
            "degree": "28"
        },
        {
            "id": "albite",
            "group": "MINERAL",
            "degree": "2"
        },
        {
            "id": "gold deposit",
            "group": "ORE_DEPOSIT",
            "degree": "24"
        },
        {
            "id": "olivine",
            "group": "MINERAL",
            "degree": "6"
        },
        {
            "id": "lode deposit",
            "group": "ORE_DEPOSIT",
            "degree": "2"
        },
        {
            "id": "chromium",
            "group": "MINERAL",
            "degree": "2"
        },
        {
            "id": "tin",
            "group": "MINERAL",
            "degree": "2"
        },
        {
            "id": "tremolite",
            "group": "MINERAL",
            "degree": "6"
        },
        {
            "id": "aluminium",
            "group": "MINERAL",
            "degree": "2"
        },
        {
            "id": "zircon",
            "group": "MINERAL",
            "degree": "2"
        },
        {
            "id": "opaline",
            "group": "MINERAL",
            "degree": "4"
        },
        {
            "id": "oxide gold deposits",
            "group": "ORE_DEPOSIT",
            "degree": "3"
        },
        {
            "id": "hornblende",
            "group": "MINERAL",
            "degree": "8"
        },
        {
            "id": "biotite",
            "group": "MINERAL",
            "degree": "18"
        },
        {
            "id": "chlorite",
            "group": "MINERAL",
            "degree": "26"
        },
        {
            "id": "quartz",
            "group": "MINERAL",
            "degree": "56"
        },
        {
            "id": "antimony",
            "group": "MINERAL",
            "degree": "2"
        },
        {
            "id": "iron",
            "group": "MINERAL",
            "degree": "10"
        },
        {
            "id": "chalcopyrite",
            "group": "MINERAL",
            "degree": "12"
        },
        {
            "id": "garnet",
            "group": "MINERAL",
            "degree": "1"
        },
        {
            "id": "actinolite",
            "group": "MINERAL",
            "degree": "8"
        },
        {
            "id": "lead",
            "group": "MINERAL",
            "degree": "2"
        },
        {
            "id": "tourmaline",
            "group": "MINERAL",
            "degree": "6"
        },
        {
            "id": "sphalerite",
            "group": "MINERAL",
            "degree": "7"
        },
        {
            "id": "alluvial gold",
            "group": "MINERAL",
            "degree": "2"
        },
        {
            "id": "hydrothermal",
            "group": "MINERAL",
            "degree": "11"
        },
        {
            "id": "plasma",
            "group": "MINERAL",
            "degree": "1"
        },
        {
            "id": "oxide",
            "group": "MINERAL",
            "degree": "7"
        },
        {
            "id": "gold",
            "group": "MINERAL",
            "degree": "114"
        },
        {
            "id": "talc",
            "group": "MINERAL",
            "degree": "19"
        },
        {
            "id": "plagioclase",
            "group": "MINERAL",
            "degree": "8"
        },
        {
            "id": "supergene",
            "group": "ORE_DEPOSIT",
            "degree": "6"
        },
        {
            "id": "silica",
            "group": "MINERAL",
            "degree": "8"
        },
        {
            "id": "galena",
            "group": "MINERAL",
            "degree": "7"
        },
        {
            "id": "pyrite",
            "group": "MINERAL",
            "degree": "19"
        },
        {
            "id": "amphibole",
            "group": "MINERAL",
            "degree": "5"
        },
        {
            "id": "cerium",
            "group": "MINERAL",
            "degree": "1"
        },
        {
            "id": "pyrrhotite",
            "group": "MINERAL",
            "degree": "19"
        },
        {
            "id": "zinc",
            "group": "MINERAL",
            "degree": "3"
        },
        {
            "id": "ilmenite",
            "group": "MINERAL",
            "degree": "8"
        },
        {
            "id": "arsenopyrite",
            "group": "MINERAL",
            "degree": "6"
        }
    ],
    "links": [
        {
            "source": "nickel",
            "target": "chromium",
            "label": ""
        },
        {
            "source": "nickel",
            "target": "gold",
            "label": ""
        },
        {
            "source": "tungsten",
            "target": "antimony",
            "label": ""
        },
        {
            "source": "arsenic",
            "target": "gold",
            "label": ""
        },
        {
            "source": "arsenic",
            "target": "lead",
            "label": ""
        },
        {
            "source": "lode gold deposit",
            "target": "gold",
            "label": ""
        },
        {
            "source": "lode gold deposit",
            "target": "supergene",
            "label": ""
        },
        {
            "source": "anthophyllite",
            "target": "actinolite",
            "label": ""
        },
        {
            "source": "carbonate",
            "target": "quartz",
            "label": ""
        },
        {
            "source": "carbonate",
            "target": "biotite",
            "label": ""
        },
        {
            "source": "carbonate",
            "target": "pyrrhotite",
            "label": ""
        },
        {
            "source": "lode",
            "target": "quartz",
            "label": "contains"
        },
        {
            "source": "lode",
            "target": "oxide",
            "label": ""
        },
        {
            "source": "lode",
            "target": "gold",
            "label": ""
        },
        {
            "source": "lode",
            "target": "lode gold deposit",
            "label": ""
        },
        {
            "source": "lode",
            "target": "sulphide",
            "label": ""
        },
        {
            "source": "lode",
            "target": "pyrite",
            "label": ""
        },
        {
            "source": "sulphide",
            "target": "gold",
            "label": "associated_with"
        },
        {
            "source": "sulphide",
            "target": "pyrrhotite",
            "label": "contains"
        },
        {
            "source": "sulphide",
            "target": "quartz",
            "label": ""
        },
        {
            "source": "sulphide",
            "target": "lode",
            "label": ""
        },
        {
            "source": "sulphide",
            "target": "lode deposit",
            "label": ""
        },
        {
            "source": "sulphide",
            "target": "arsenic",
            "label": ""
        },
        {
            "source": "sulphide",
            "target": "arsenopyrite",
            "label": "contains"
        },
        {
            "source": "gold deposit",
            "target": "quartz",
            "label": "associated_with"
        },
        {
            "source": "gold deposit",
            "target": "hydrothermal",
            "label": ""
        },
        {
            "source": "gold deposit",
            "target": "gold",
            "label": ""
        },
        {
            "source": "gold deposit",
            "target": "lode",
            "label": "associated_with"
        },
        {
            "source": "lode deposit",
            "target": "gold",
            "label": ""
        },
        {
            "source": "tin",
            "target": "aluminium",
            "label": ""
        },
        {
            "source": "aluminium",
            "target": "zircon",
            "label": ""
        },
        {
            "source": "zircon",
            "target": "cerium",
            "label": ""
        },
        {
            "source": "opaline",
            "target": "talc",
            "label": ""
        },
        {
            "source": "oxide gold deposits",
            "target": "gold",
            "label": ""
        },
        {
            "source": "hornblende",
            "target": "tremolite",
            "label": "in"
        },
        {
            "source": "hornblende",
            "target": "chlorite",
            "label": "in"
        },
        {
            "source": "hornblende",
            "target": "talc",
            "label": "in"
        },
        {
            "source": "hornblende",
            "target": "carbonate",
            "label": "in"
        },
        {
            "source": "hornblende",
            "target": "olivine",
            "label": "in"
        },
        {
            "source": "hornblende",
            "target": "anthophyllite",
            "label": "in"
        },
        {
            "source": "biotite",
            "target": "gold",
            "label": "associated_with"
        },
        {
            "source": "biotite",
            "target": "albite",
            "label": "in"
        },
        {
            "source": "biotite",
            "target": "pyrite",
            "label": ""
        },
        {
            "source": "biotite",
            "target": "carbonate",
            "label": ""
        },
        {
            "source": "biotite",
            "target": "sulphide",
            "label": ""
        },
        {
            "source": "biotite",
            "target": "chlorite",
            "label": ""
        },
        {
            "source": "chlorite",
            "target": "quartz",
            "label": ""
        },
        {
            "source": "chlorite",
            "target": "biotite",
            "label": ""
        },
        {
            "source": "chlorite",
            "target": "pyrrhotite",
            "label": ""
        },
        {
            "source": "chlorite",
            "target": "opaline",
            "label": ""
        },
        {
            "source": "chlorite",
            "target": "silica",
            "label": ""
        },
        {
            "source": "chlorite",
            "target": "carbonate",
            "label": ""
        },
        {
            "source": "chlorite",
            "target": "tourmaline",
            "label": ""
        },
        {
            "source": "chlorite",
            "target": "sulphide",
            "label": ""
        },
        {
            "source": "chlorite",
            "target": "talc",
            "label": "dominated_by"
        },
        {
            "source": "quartz",
            "target": "iron",
            "label": "in"
        },
        {
            "source": "quartz",
            "target": "pyrrhotite",
            "label": ""
        },
        {
            "source": "quartz",
            "target": "gold",
            "label": ""
        },
        {
            "source": "quartz",
            "target": "lode",
            "label": "contains"
        },
        {
            "source": "quartz",
            "target": "sulphide",
            "label": ""
        },
        {
            "source": "quartz",
            "target": "talc",
            "label": ""
        },
        {
            "source": "quartz",
            "target": "tourmaline",
            "label": ""
        },
        {
            "source": "quartz",
            "target": "chalcopyrite",
            "label": ""
        },
        {
            "source": "quartz",
            "target": "pyrite",
            "label": ""
        },
        {
            "source": "antimony",
            "target": "gold",
            "label": ""
        },
        {
            "source": "iron",
            "target": "gold",
            "label": ""
        },
        {
            "source": "chalcopyrite",
            "target": "quartz",
            "label": "contains"
        },
        {
            "source": "chalcopyrite",
            "target": "galena",
            "label": ""
        },
        {
            "source": "chalcopyrite",
            "target": "pyrite",
            "label": ""
        },
        {
            "source": "chalcopyrite",
            "target": "lode",
            "label": "contains"
        },
        {
            "source": "chalcopyrite",
            "target": "sulphide",
            "label": ""
        },
        {
            "source": "actinolite",
            "target": "tremolite",
            "label": "in"
        },
        {
            "source": "actinolite",
            "target": "chlorite",
            "label": "in"
        },
        {
            "source": "actinolite",
            "target": "talc",
            "label": "in"
        },
        {
            "source": "actinolite",
            "target": "carbonate",
            "label": "in"
        },
        {
            "source": "actinolite",
            "target": "olivine",
            "label": "in"
        },
        {
            "source": "actinolite",
            "target": "anthophyllite",
            "label": "in"
        },
        {
            "source": "tourmaline",
            "target": "quartz",
            "label": "contains"
        },
        {
            "source": "tourmaline",
            "target": "lode",
            "label": "contains"
        },
        {
            "source": "sphalerite",
            "target": "chalcopyrite",
            "label": "contains"
        },
        {
            "source": "sphalerite",
            "target": "galena",
            "label": "contains"
        },
        {
            "source": "sphalerite",
            "target": "pyrite",
            "label": ""
        },
        {
            "source": "sphalerite",
            "target": "pyrrhotite",
            "label": ""
        },
        {
            "source": "oxide",
            "target": "lode",
            "label": ""
        },
        {
            "source": "oxide",
            "target": "gold",
            "label": ""
        },
        {
            "source": "gold",
            "target": "sulphide",
            "label": "in;associated_with;occurs_in;hosted_in"
        },
        {
            "source": "gold",
            "target": "supergene",
            "label": "dominated_by"
        },
        {
            "source": "gold",
            "target": "arsenopyrite",
            "label": "associated_with"
        },
        {
            "source": "gold",
            "target": "pyrrhotite",
            "label": "associated_with;hosted_in"
        },
        {
            "source": "gold",
            "target": "biotite",
            "label": "associated_with"
        },
        {
            "source": "gold",
            "target": "chlorite",
            "label": "associated_with"
        },
        {
            "source": "gold",
            "target": "talc",
            "label": "associated_with"
        },
        {
            "source": "gold",
            "target": "carbonate",
            "label": "associated_with"
        },
        {
            "source": "gold",
            "target": "tourmaline",
            "label": "associated_with"
        },
        {
            "source": "gold",
            "target": "quartz",
            "label": "occurs_in;associated_with"
        },
        {
            "source": "gold",
            "target": "chalcopyrite",
            "label": "associated_with"
        },
        {
            "source": "gold",
            "target": "pyrite",
            "label": "associated_with"
        },
        {
            "source": "gold",
            "target": "arsenic",
            "label": "in"
        },
        {
            "source": "gold",
            "target": "hydrothermal",
            "label": "associated_with"
        },
        {
            "source": "gold",
            "target": "gold deposit",
            "label": "in;dominated_by"
        },
        {
            "source": "gold",
            "target": "lode",
            "label": "occurs_in;in"
        },
        {
            "source": "gold",
            "target": "iron",
            "label": ""
        },
        {
            "source": "gold",
            "target": "plasma",
            "label": ""
        },
        {
            "source": "gold",
            "target": "lead",
            "label": ""
        },
        {
            "source": "gold",
            "target": "nickel",
            "label": ""
        },
        {
            "source": "gold",
            "target": "sphalerite",
            "label": ""
        },
        {
            "source": "gold",
            "target": "oxide",
            "label": ""
        },
        {
            "source": "talc",
            "target": "opaline",
            "label": ""
        },
        {
            "source": "talc",
            "target": "silica",
            "label": ""
        },
        {
            "source": "talc",
            "target": "hornblende",
            "label": ""
        },
        {
            "source": "talc",
            "target": "biotite",
            "label": ""
        },
        {
            "source": "talc",
            "target": "amphibole",
            "label": ""
        },
        {
            "source": "plagioclase",
            "target": "tremolite",
            "label": "in"
        },
        {
            "source": "plagioclase",
            "target": "chlorite",
            "label": "in"
        },
        {
            "source": "plagioclase",
            "target": "talc",
            "label": "in"
        },
        {
            "source": "plagioclase",
            "target": "carbonate",
            "label": "in"
        },
        {
            "source": "plagioclase",
            "target": "olivine",
            "label": "in"
        },
        {
            "source": "plagioclase",
            "target": "anthophyllite",
            "label": "in"
        },
        {
            "source": "supergene",
            "target": "oxide gold deposits",
            "label": ""
        },
        {
            "source": "supergene",
            "target": "lode gold deposit",
            "label": ""
        },
        {
            "source": "silica",
            "target": "biotite",
            "label": "associated_with"
        },
        {
            "source": "silica",
            "target": "chlorite",
            "label": "associated_with"
        },
        {
            "source": "silica",
            "target": "quartz",
            "label": ""
        },
        {
            "source": "galena",
            "target": "pyrrhotite",
            "label": ""
        },
        {
            "source": "galena",
            "target": "chalcopyrite",
            "label": ""
        },
        {
            "source": "galena",
            "target": "gold",
            "label": ""
        },
        {
            "source": "pyrite",
            "target": "quartz",
            "label": "contains"
        },
        {
            "source": "pyrite",
            "target": "biotite",
            "label": ""
        },
        {
            "source": "pyrite",
            "target": "pyrrhotite",
            "label": "in"
        },
        {
            "source": "pyrite",
            "target": "chlorite",
            "label": ""
        },
        {
            "source": "pyrite",
            "target": "gold",
            "label": ""
        },
        {
            "source": "pyrite",
            "target": "lode",
            "label": "contains"
        },
        {
            "source": "amphibole",
            "target": "opaline",
            "label": ""
        },
        {
            "source": "amphibole",
            "target": "silica",
            "label": ""
        },
        {
            "source": "pyrrhotite",
            "target": "quartz",
            "label": "in"
        },
        {
            "source": "pyrrhotite",
            "target": "biotite",
            "label": ""
        },
        {
            "source": "pyrrhotite",
            "target": "pyrite",
            "label": ""
        },
        {
            "source": "pyrrhotite",
            "target": "galena",
            "label": ""
        },
        {
            "source": "pyrrhotite",
            "target": "sphalerite",
            "label": ""
        },
        {
            "source": "pyrrhotite",
            "target": "chalcopyrite",
            "label": ""
        },
        {
            "source": "pyrrhotite",
            "target": "gold",
            "label": ""
        },
        {
            "source": "pyrrhotite",
            "target": "sulphide",
            "label": ""
        },
        {
            "source": "zinc",
            "target": "nickel",
            "label": ""
        },
        {
            "source": "zinc",
            "target": "chromium",
            "label": ""
        },
        {
            "source": "ilmenite",
            "target": "tremolite",
            "label": "in"
        },
        {
            "source": "ilmenite",
            "target": "chlorite",
            "label": "in"
        },
        {
            "source": "ilmenite",
            "target": "talc",
            "label": "in"
        },
        {
            "source": "ilmenite",
            "target": "carbonate",
            "label": "in"
        },
        {
            "source": "ilmenite",
            "target": "olivine",
            "label": "in"
        },
        {
            "source": "ilmenite",
            "target": "anthophyllite",
            "label": "in"
        },
        {
            "source": "arsenopyrite",
            "target": "pyrite",
            "label": ""
        },
        {
            "source": "arsenopyrite",
            "target": "galena",
            "label": ""
        },
        {
            "source": "arsenopyrite",
            "target": "sphalerite",
            "label": ""
        },
        {
            "source": "arsenopyrite",
            "target": "chalcopyrite",
            "label": ""
        }
    ]
}